pydra/tasks/mrtrix3/__init__.py
pydra/tasks/mrtrix3/_version.py
pydra/tasks/mrtrix3/latest.py
pydra/tasks/mrtrix3/manual/mrcalc.py
pydra/tasks/mrtrix3/v3_1/__init__.py
pydra/tasks/mrtrix3/v3_1/afdconnectivity.py
pydra/tasks/mrtrix3/v3_1/amp2response.py
pydra/tasks/mrtrix3/v3_1/amp2sh.py
pydra/tasks/mrtrix3/v3_1/connectome2tck.py
pydra/tasks/mrtrix3/v3_1/connectomeedit.py
pydra/tasks/mrtrix3/v3_1/connectomestats.py
pydra/tasks/mrtrix3/v3_1/dcmedit.py
pydra/tasks/mrtrix3/v3_1/dcminfo.py
pydra/tasks/mrtrix3/v3_1/dirflip.py
pydra/tasks/mrtrix3/v3_1/dirgen.py
pydra/tasks/mrtrix3/v3_1/dirmerge.py
pydra/tasks/mrtrix3/v3_1/dirorder.py
pydra/tasks/mrtrix3/v3_1/dirrotate.py
pydra/tasks/mrtrix3/v3_1/dirsplit.py
pydra/tasks/mrtrix3/v3_1/dirstat.py
pydra/tasks/mrtrix3/v3_1/dwi2adc.py
pydra/tasks/mrtrix3/v3_1/dwi2fod.py
pydra/tasks/mrtrix3/v3_1/dwi2mask_3dautomask.py
pydra/tasks/mrtrix3/v3_1/dwi2mask_ants.py
pydra/tasks/mrtrix3/v3_1/dwi2mask_b02template.py
pydra/tasks/mrtrix3/v3_1/dwi2mask_consensus.py
pydra/tasks/mrtrix3/v3_1/dwi2mask_fslbet.py
pydra/tasks/mrtrix3/v3_1/dwi2mask_hdbet.py
pydra/tasks/mrtrix3/v3_1/dwi2mask_legacy.py
pydra/tasks/mrtrix3/v3_1/dwi2mask_mean.py
pydra/tasks/mrtrix3/v3_1/dwi2mask_mtnorm.py
pydra/tasks/mrtrix3/v3_1/dwi2mask_synthstrip.py
pydra/tasks/mrtrix3/v3_1/dwi2mask_trace.py
pydra/tasks/mrtrix3/v3_1/dwi2response_dhollander.py
pydra/tasks/mrtrix3/v3_1/dwi2response_fa.py
pydra/tasks/mrtrix3/v3_1/dwi2response_manual.py
pydra/tasks/mrtrix3/v3_1/dwi2response_msmt_5tt.py
pydra/tasks/mrtrix3/v3_1/dwi2response_tax.py
pydra/tasks/mrtrix3/v3_1/dwi2response_tournier.py
pydra/tasks/mrtrix3/v3_1/dwi2tensor.py
pydra/tasks/mrtrix3/v3_1/dwibiascorrect_ants.py
pydra/tasks/mrtrix3/v3_1/dwibiascorrect_fsl.py
pydra/tasks/mrtrix3/v3_1/dwibiascorrect_mtnorm.py
pydra/tasks/mrtrix3/v3_1/dwibiasnormmask.py
pydra/tasks/mrtrix3/v3_1/dwicat.py
pydra/tasks/mrtrix3/v3_1/dwidenoise.py
pydra/tasks/mrtrix3/v3_1/dwiextract.py
pydra/tasks/mrtrix3/v3_1/dwifslpreproc.py
pydra_tasks_mrtrix3-3.1.0a4.dist-info/METADATA
pydra_tasks_mrtrix3-3.1.0a4.dist-info/WHEEL
pydra_tasks_mrtrix3-3.1.0a4.dist-info/licenses/LICENSE
pydra_tasks_mrtrix3-3.1.0a4.dist-info/RECORD
