Metadata-Version: 2.4
Name: pydra-tasks-mrtrix3
Version: 3.1.0a4
Summary: pydra-tasks-mrtrix3 contains Pydra task specifications for MRtrix3 tools
Author-email: "Thomas G. Close" <tom.g.close@gmail.com>
Maintainer-email: "Thomas G. Close" <tom.g.close@gmail.com>
License:    Copyright 2022 Nipype developers
License-File: LICENSE
Keywords: pydra
Classifier: Development Status :: 2 - Pre-Alpha
Classifier: Environment :: Console
Classifier: Intended Audience :: Science/Research
Classifier: License :: OSI Approved :: Apache Software License
Classifier: Operating System :: MacOS :: MacOS X
Classifier: Operating System :: POSIX :: Linux
Classifier: Programming Language :: Python :: 3
Classifier: Topic :: Scientific/Engineering
Requires-Python: >=3.11
Requires-Dist: fileformats-medimage-mrtrix3>=3.0.4a5
Requires-Dist: numpy
Requires-Dist: pydra>=1.0a2
Provides-Extra: dev
Requires-Dist: attrs>=23.1.0; extra == 'dev'
Requires-Dist: black; extra == 'dev'
Requires-Dist: black>=22.12.0; extra == 'dev'
Requires-Dist: click>=8.1.3; extra == 'dev'
Requires-Dist: fileformats-extras>=0.12.1; extra == 'dev'
Requires-Dist: pre-commit; extra == 'dev'
Requires-Dist: tqdm; extra == 'dev'
Provides-Extra: doc
Requires-Dist: packaging; extra == 'doc'
Requires-Dist: sphinx-rtd-theme; extra == 'doc'
Requires-Dist: sphinx>=2.1.2; extra == 'doc'
Requires-Dist: sphinxcontrib-apidoc~=0.3.0; extra == 'doc'
Requires-Dist: sphinxcontrib-napoleon; extra == 'doc'
Requires-Dist: sphinxcontrib-versioning; extra == 'doc'
Provides-Extra: test
Requires-Dist: codecov; extra == 'test'
Requires-Dist: fileformats-medimage-mrtrix3-extras; extra == 'test'
Requires-Dist: pytest-cov; extra == 'test'
Requires-Dist: pytest-env; extra == 'test'
Requires-Dist: pytest-rerunfailures; extra == 'test'
Requires-Dist: pytest-xdist; extra == 'test'
Requires-Dist: pytest>=4.4.0; extra == 'test'
